README.md
setup.py
aiosched/__init__.py
aiosched/aiosched.py
aiosched.egg-info/PKG-INFO
aiosched.egg-info/SOURCES.txt
aiosched.egg-info/dependency_links.txt
aiosched.egg-info/top_level.txt