Metadata-Version: 2.1
Name: aiosched
Version: 0.0.6
Summary: asyncio job scheduler
Home-page: https://github.com/alttch/aiosched
Author: Altertech
Author-email: div@altertech.com
License: MIT
Platform: UNKNOWN
Classifier: Programming Language :: Python :: 3
Classifier: License :: OSI Approved :: MIT License
Classifier: Topic :: Software Development :: Libraries
